.coveragerc
CHANGELOG.rst
LICENSE
MANIFEST.in
README.rst
pytest.ini
setup.py
docs/Makefile
docs/conf.py
docs/index.rst
docs/_static/custom.css
src/epiweeks.py
src/epiweeks.egg-info/PKG-INFO
src/epiweeks.egg-info/SOURCES.txt
src/epiweeks.egg-info/dependency_links.txt
src/epiweeks.egg-info/top_level.txt
src/epiweeks_barc.egg-info/PKG-INFO
src/epiweeks_barc.egg-info/SOURCES.txt
src/epiweeks_barc.egg-info/dependency_links.txt
src/epiweeks_barc.egg-info/top_level.txt
tests/other/test_reference.py
tests/other/data/cdc_weeks.json
tests/other/data/iso_weeks.json
tests/unit/test_epiweeks.py