Metadata-Version: 2.1
Name: epiweeks-barc
Version: 0.0.1
Summary: Epidemiological weeks based on the CDC (MMWR) and ISO week numbering systems.
Home-page: https://github.com/ankusharya/epiweeks
Author: Ankush Singh
Author-email: 
License: MIT
Project-URL: Documentation, https://epiweeks.readthedocs.io/
Keywords: epidemiology weeks cdc mmwr iso calendar surveillance public-health
Platform: UNKNOWN
Classifier: Development Status :: 5 - Production/Stable
Classifier: Intended Audience :: Developers
Classifier: Intended Audience :: Healthcare Industry
Classifier: Intended Audience :: Telecommunications Industry
Classifier: Intended Audience :: Science/Research
Classifier: License :: OSI Approved :: MIT License
Classifier: Natural Language :: English
Classifier: Programming Language :: Python
Classifier: Programming Language :: Python :: 3
Classifier: Programming Language :: Python :: 3.6
Classifier: Programming Language :: Python :: 3.7
Classifier: Topic :: Scientific/Engineering
Classifier: Topic :: Utilities
Classifier: Typing :: Typed
Requires-Python: >=3.6
